[
  {
    "faculty": "Escola Tècnica Superior d'Arquitectura",
    "total_courses": 69,
    "courses_with_sdgs": 69,
    "sdg_coverage_percent": 100,
    "sdgs": {
      "SDG-01": 35,
      "SDG-02": 32,
      "SDG-03": 46,
      "SDG-04": 49,
      "SDG-05": 29,
      "SDG-06": 24,
      "SDG-07": 8,
      "SDG-08": 53,
      "SDG-09": 56,
      "SDG-10": 52,
      "SDG-11": 53,
      "SDG-12": 28,
      "SDG-13": 21,
      "SDG-14": 16,
      "SDG-15": 36,
      "SDG-16": 43,
      "SDG-17": 19
    },
    "percentages": {
      "SDG-01": 5.8,
      "SDG-02": 5.3,
      "SDG-03": 7.7,
      "SDG-04": 8.2,
      "SDG-05": 4.8,
      "SDG-06": 4,
      "SDG-07": 1.3,
      "SDG-08": 8.8,
      "SDG-09": 9.3,
      "SDG-10": 8.7,
      "SDG-11": 8.8,
      "SDG-12": 4.7,
      "SDG-13": 3.5,
      "SDG-14": 2.7,
      "SDG-15": 6,
      "SDG-16": 7.2,
      "SDG-17": 3.2
    }
  },
  {
    "faculty": "Escola Tècnica Superior d'Enginyeria",
    "total_courses": 362,
    "courses_with_sdgs": 361,
    "sdg_coverage_percent": 99.7,
    "sdgs": {
      "SDG-01": 248,
      "SDG-02": 225,
      "SDG-03": 290,
      "SDG-04": 290,
      "SDG-05": 146,
      "SDG-06": 151,
      "SDG-07": 93,
      "SDG-08": 297,
      "SDG-09": 306,
      "SDG-10": 325,
      "SDG-11": 285,
      "SDG-12": 219,
      "SDG-13": 93,
      "SDG-14": 60,
      "SDG-15": 221,
      "SDG-16": 298,
      "SDG-17": 136
    },
    "percentages": {
      "SDG-01": 6.7,
      "SDG-02": 6.1,
      "SDG-03": 7.9,
      "SDG-04": 7.9,
      "SDG-05": 4,
      "SDG-06": 4.1,
      "SDG-07": 2.5,
      "SDG-08": 8.1,
      "SDG-09": 8.3,
      "SDG-10": 8.8,
      "SDG-11": 7.7,
      "SDG-12": 5.9,
      "SDG-13": 2.5,
      "SDG-14": 1.6,
      "SDG-15": 6,
      "SDG-16": 8.1,
      "SDG-17": 3.7
    }
  },
  {
    "faculty": "Escola Tècnica Superior d'Enginyeria Química",
    "total_courses": 206,
    "courses_with_sdgs": 197,
    "sdg_coverage_percent": 95.6,
    "sdgs": {
      "SDG-01": 128,
      "SDG-02": 106,
      "SDG-03": 155,
      "SDG-04": 163,
      "SDG-05": 81,
      "SDG-06": 87,
      "SDG-07": 55,
      "SDG-08": 166,
      "SDG-09": 167,
      "SDG-10": 173,
      "SDG-11": 156,
      "SDG-12": 100,
      "SDG-13": 58,
      "SDG-14": 32,
      "SDG-15": 123,
      "SDG-16": 169,
      "SDG-17": 85
    },
    "percentages": {
      "SDG-01": 6.4,
      "SDG-02": 5.3,
      "SDG-03": 7.7,
      "SDG-04": 8.1,
      "SDG-05": 4,
      "SDG-06": 4.3,
      "SDG-07": 2.7,
      "SDG-08": 8.3,
      "SDG-09": 8.3,
      "SDG-10": 8.6,
      "SDG-11": 7.8,
      "SDG-12": 5,
      "SDG-13": 2.9,
      "SDG-14": 1.6,
      "SDG-15": 6.1,
      "SDG-16": 8.4,
      "SDG-17": 4.2
    }
  },
  {
    "faculty": "Facultat d'Economia i Empresa",
    "total_courses": 204,
    "courses_with_sdgs": 204,
    "sdg_coverage_percent": 100,
    "sdgs": {
      "SDG-01": 133,
      "SDG-02": 117,
      "SDG-03": 151,
      "SDG-04": 157,
      "SDG-05": 114,
      "SDG-06": 86,
      "SDG-07": 68,
      "SDG-08": 168,
      "SDG-09": 168,
      "SDG-10": 186,
      "SDG-11": 159,
      "SDG-12": 124,
      "SDG-13": 63,
      "SDG-14": 41,
      "SDG-15": 154,
      "SDG-16": 161,
      "SDG-17": 75
    },
    "percentages": {
      "SDG-01": 6.3,
      "SDG-02": 5.5,
      "SDG-03": 7.1,
      "SDG-04": 7.4,
      "SDG-05": 5.4,
      "SDG-06": 4,
      "SDG-07": 3.2,
      "SDG-08": 7.9,
      "SDG-09": 7.9,
      "SDG-10": 8.8,
      "SDG-11": 7.5,
      "SDG-12": 5.8,
      "SDG-13": 3,
      "SDG-14": 1.9,
      "SDG-15": 7.2,
      "SDG-16": 7.6,
      "SDG-17": 3.5
    }
  },
  {
    "faculty": "Facultat d'Enologia",
    "total_courses": 201,
    "courses_with_sdgs": 177,
    "sdg_coverage_percent": 88.1,
    "sdgs": {
      "SDG-01": 104,
      "SDG-02": 90,
      "SDG-03": 124,
      "SDG-04": 133,
      "SDG-05": 78,
      "SDG-06": 63,
      "SDG-07": 19,
      "SDG-08": 140,
      "SDG-09": 127,
      "SDG-10": 157,
      "SDG-11": 122,
      "SDG-12": 95,
      "SDG-13": 30,
      "SDG-14": 42,
      "SDG-15": 96,
      "SDG-16": 129,
      "SDG-17": 56
    },
    "percentages": {
      "SDG-01": 6.5,
      "SDG-02": 5.6,
      "SDG-03": 7.7,
      "SDG-04": 8.3,
      "SDG-05": 4.9,
      "SDG-06": 3.9,
      "SDG-07": 1.2,
      "SDG-08": 8.7,
      "SDG-09": 7.9,
      "SDG-10": 9.8,
      "SDG-11": 7.6,
      "SDG-12": 5.9,
      "SDG-13": 1.9,
      "SDG-14": 2.6,
      "SDG-15": 6,
      "SDG-16": 8,
      "SDG-17": 3.5
    }
  },
  {
    "faculty": "Facultat d'Infermeria",
    "total_courses": 68,
    "courses_with_sdgs": 68,
    "sdg_coverage_percent": 100,
    "sdgs": {
      "SDG-01": 62,
      "SDG-02": 61,
      "SDG-03": 63,
      "SDG-04": 63,
      "SDG-05": 47,
      "SDG-06": 44,
      "SDG-07": 33,
      "SDG-08": 66,
      "SDG-09": 65,
      "SDG-10": 66,
      "SDG-11": 65,
      "SDG-12": 57,
      "SDG-13": 27,
      "SDG-14": 14,
      "SDG-15": 61,
      "SDG-16": 64,
      "SDG-17": 30
    },
    "percentages": {
      "SDG-01": 7,
      "SDG-02": 6.9,
      "SDG-03": 7.1,
      "SDG-04": 7.1,
      "SDG-05": 5.3,
      "SDG-06": 5,
      "SDG-07": 3.7,
      "SDG-08": 7.4,
      "SDG-09": 7.3,
      "SDG-10": 7.4,
      "SDG-11": 7.3,
      "SDG-12": 6.4,
      "SDG-13": 3,
      "SDG-14": 1.6,
      "SDG-15": 6.9,
      "SDG-16": 7.2,
      "SDG-17": 3.4
    }
  },
  {
    "faculty": "Facultat de Ciències Jurídiques",
    "total_courses": 280,
    "courses_with_sdgs": 278,
    "sdg_coverage_percent": 99.3,
    "sdgs": {
      "SDG-01": 183,
      "SDG-02": 164,
      "SDG-03": 200,
      "SDG-04": 223,
      "SDG-05": 104,
      "SDG-06": 113,
      "SDG-07": 75,
      "SDG-08": 249,
      "SDG-09": 238,
      "SDG-10": 252,
      "SDG-11": 231,
      "SDG-12": 155,
      "SDG-13": 62,
      "SDG-14": 35,
      "SDG-15": 185,
      "SDG-16": 218,
      "SDG-17": 88
    },
    "percentages": {
      "SDG-01": 6.6,
      "SDG-02": 5.9,
      "SDG-03": 7.2,
      "SDG-04": 8,
      "SDG-05": 3.7,
      "SDG-06": 4.1,
      "SDG-07": 2.7,
      "SDG-08": 9,
      "SDG-09": 8.6,
      "SDG-10": 9.1,
      "SDG-11": 8.3,
      "SDG-12": 5.6,
      "SDG-13": 2.2,
      "SDG-14": 1.3,
      "SDG-15": 6.7,
      "SDG-16": 7.9,
      "SDG-17": 3.2
    }
  },
  {
    "faculty": "Facultat de Ciències de l'Educació i Psicologia",
    "total_courses": 288,
    "courses_with_sdgs": 286,
    "sdg_coverage_percent": 99.3,
    "sdgs": {
      "SDG-01": 183,
      "SDG-02": 159,
      "SDG-03": 230,
      "SDG-04": 217,
      "SDG-05": 122,
      "SDG-06": 141,
      "SDG-07": 85,
      "SDG-08": 241,
      "SDG-09": 244,
      "SDG-10": 246,
      "SDG-11": 226,
      "SDG-12": 179,
      "SDG-13": 76,
      "SDG-14": 47,
      "SDG-15": 196,
      "SDG-16": 222,
      "SDG-17": 91
    },
    "percentages": {
      "SDG-01": 6.3,
      "SDG-02": 5.5,
      "SDG-03": 7.9,
      "SDG-04": 7.5,
      "SDG-05": 4.2,
      "SDG-06": 4.9,
      "SDG-07": 2.9,
      "SDG-08": 8.3,
      "SDG-09": 8.4,
      "SDG-10": 8.5,
      "SDG-11": 7.8,
      "SDG-12": 6.2,
      "SDG-13": 2.6,
      "SDG-14": 1.6,
      "SDG-15": 6.7,
      "SDG-16": 7.6,
      "SDG-17": 3.1
    }
  },
  {
    "faculty": "Facultat de Lletres",
    "total_courses": 372,
    "courses_with_sdgs": 370,
    "sdg_coverage_percent": 99.5,
    "sdgs": {
      "SDG-01": 229,
      "SDG-02": 208,
      "SDG-03": 265,
      "SDG-04": 316,
      "SDG-05": 129,
      "SDG-06": 140,
      "SDG-07": 115,
      "SDG-08": 324,
      "SDG-09": 316,
      "SDG-10": 321,
      "SDG-11": 304,
      "SDG-12": 224,
      "SDG-13": 101,
      "SDG-14": 39,
      "SDG-15": 236,
      "SDG-16": 293,
      "SDG-17": 124
    },
    "percentages": {
      "SDG-01": 6.2,
      "SDG-02": 5.6,
      "SDG-03": 7.2,
      "SDG-04": 8.6,
      "SDG-05": 3.5,
      "SDG-06": 3.8,
      "SDG-07": 3.1,
      "SDG-08": 8.8,
      "SDG-09": 8.6,
      "SDG-10": 8.7,
      "SDG-11": 8.3,
      "SDG-12": 6.1,
      "SDG-13": 2.7,
      "SDG-14": 1.1,
      "SDG-15": 6.4,
      "SDG-16": 8,
      "SDG-17": 3.4
    }
  },
  {
    "faculty": "Facultat de Medicina i Ciències de la Salut",
    "total_courses": 208,
    "courses_with_sdgs": 208,
    "sdg_coverage_percent": 100,
    "sdgs": {
      "SDG-01": 117,
      "SDG-02": 109,
      "SDG-03": 166,
      "SDG-04": 145,
      "SDG-05": 67,
      "SDG-06": 79,
      "SDG-07": 21,
      "SDG-08": 148,
      "SDG-09": 161,
      "SDG-10": 163,
      "SDG-11": 147,
      "SDG-12": 105,
      "SDG-13": 35,
      "SDG-14": 25,
      "SDG-15": 123,
      "SDG-16": 142,
      "SDG-17": 64
    },
    "percentages": {
      "SDG-01": 6.4,
      "SDG-02": 6,
      "SDG-03": 9.1,
      "SDG-04": 8,
      "SDG-05": 3.7,
      "SDG-06": 4.3,
      "SDG-07": 1.2,
      "SDG-08": 8.1,
      "SDG-09": 8.9,
      "SDG-10": 9,
      "SDG-11": 8.1,
      "SDG-12": 5.8,
      "SDG-13": 1.9,
      "SDG-14": 1.4,
      "SDG-15": 6.8,
      "SDG-16": 7.8,
      "SDG-17": 3.5
    }
  },
  {
    "faculty": "Facultat de Química",
    "total_courses": 203,
    "courses_with_sdgs": 203,
    "sdg_coverage_percent": 100,
    "sdgs": {
      "SDG-01": 138,
      "SDG-02": 136,
      "SDG-03": 158,
      "SDG-04": 171,
      "SDG-05": 61,
      "SDG-06": 62,
      "SDG-07": 48,
      "SDG-08": 187,
      "SDG-09": 166,
      "SDG-10": 184,
      "SDG-11": 160,
      "SDG-12": 112,
      "SDG-13": 31,
      "SDG-14": 13,
      "SDG-15": 130,
      "SDG-16": 169,
      "SDG-17": 73
    },
    "percentages": {
      "SDG-01": 6.9,
      "SDG-02": 6.8,
      "SDG-03": 7.9,
      "SDG-04": 8.6,
      "SDG-05": 3.1,
      "SDG-06": 3.1,
      "SDG-07": 2.4,
      "SDG-08": 9.4,
      "SDG-09": 8.3,
      "SDG-10": 9.2,
      "SDG-11": 8,
      "SDG-12": 5.6,
      "SDG-13": 1.6,
      "SDG-14": 0.7,
      "SDG-15": 6.5,
      "SDG-16": 8.5,
      "SDG-17": 3.7
    }
  },
  {
    "faculty": "Facultat de Turisme i Geografia",
    "total_courses": 118,
    "courses_with_sdgs": 117,
    "sdg_coverage_percent": 99.2,
    "sdgs": {
      "SDG-01": 62,
      "SDG-02": 43,
      "SDG-03": 78,
      "SDG-04": 92,
      "SDG-05": 36,
      "SDG-06": 47,
      "SDG-07": 30,
      "SDG-08": 104,
      "SDG-09": 108,
      "SDG-10": 107,
      "SDG-11": 99,
      "SDG-12": 57,
      "SDG-13": 21,
      "SDG-14": 9,
      "SDG-15": 55,
      "SDG-16": 85,
      "SDG-17": 28
    },
    "percentages": {
      "SDG-01": 5.8,
      "SDG-02": 4.1,
      "SDG-03": 7.4,
      "SDG-04": 8.7,
      "SDG-05": 3.4,
      "SDG-06": 4.4,
      "SDG-07": 2.8,
      "SDG-08": 9.8,
      "SDG-09": 10.2,
      "SDG-10": 10.1,
      "SDG-11": 9.3,
      "SDG-12": 5.4,
      "SDG-13": 2,
      "SDG-14": 0.8,
      "SDG-15": 5.2,
      "SDG-16": 8,
      "SDG-17": 2.6
    }
  }
]
